README.md
setup.py
villamar/__init__.py
villamar/main.py
villamar.egg-info/PKG-INFO
villamar.egg-info/SOURCES.txt
villamar.egg-info/dependency_links.txt
villamar.egg-info/top_level.txt