Metadata-Version: 2.1
Name: villamar
Version: 0.1
Summary: Esta es la descripcion
Home-page: https://github.com/villamar32/villamar
Author: Josue Villamar
Author-email: 
License: MIT
Download-URL: https://github.com/villamar32/villamar/tarball/0.1
Keywords: network,automation,python
Platform: UNKNOWN
